rdbtool/__init__.py
rdbtool/rdbtool.py
rdbtool-1.0.1.dist-info/LICENSE
rdbtool-1.0.1.dist-info/METADATA
rdbtool-1.0.1.dist-info/WHEEL
rdbtool-1.0.1.dist-info/top_level.txt
rdbtool-1.0.1.dist-info/RECORD
