Metadata-Version: 2.1
Name: rdbtool
Version: 1.0.1
Summary: A simple tool that controls dropbox files.
Home-page: https://github.com/reeve0930/rdbtool
Author: reeve0930
Author-email: reeve0930@gmail.com
License: MIT
Keywords: rdbtool rdb db dropbox
Platform: UNKNOWN
Classifier: License :: OSI Approved :: MIT License
Classifier: Programming Language :: Python :: 3.7
Classifier: Programming Language :: Python :: 3.6
Requires-Dist: dropbox
